{"id":108491,"date":"2004-05-22","venue":"Linton Park","comp":null,"result":"LINTON PARK CC WON BY 76 RUNS","season":2004,"home":"Linton Park CC","away":"Biddenden CC","inns":[{"team":"Linton Park CC","total":211,"wkts":"7","overs":"0","extras":"19  (8b, 7lb, 4w )","linton":1,"bat":[[1,"Christopher Thirkell","c & b Carl Burgess",15,0,1,1,0],[2,"Graham Walker","c Stephen Field b Lee Sugden",29,0,2,2,0],[3,"Matthew Carter","c Stephen Field b Lee Sugden",1,0,0,0,0],[4,"Trevor Back","c Stephen Field b Lee Sugden",1,0,0,0,0],[5,"Ron McCormick","c Dean Prosser b James Piper",54,0,11,0,0],[6,"Tim Thirkell","c Dean Prosser b James Matters",11,0,1,0,0],[7,"Mike Redman","b Dean Prosser",56,0,4,3,0],[8,"P- Bacon","not out",19,0,2,0,0],[9,"Darren Styles","not out",6,0,0,0,0]],"bowl":[["James Piper","5",2,17,1,0,0],["Lee Sugden","14",2,69,3,0,0],["Carl Burgess","9",1,26,1,0,0],["James Matters","4",0,18,1,0,0],["James Harrison","4",1,11,0,0,0],["Stephen Field","2",0,16,0,0,0],["R Studholme","3",0,11,0,0,0],["Dean Prosser","4",0,21,1,0,0],["Trevor Hills","1",0,7,0,0,0]],"fow":[]},{"team":"Biddenden CC","total":135,"wkts":"10","overs":"0","extras":"17  (7b, 8lb, 2w )","linton":0,"bat":[[1,"Martyn Summers","b Darren Styles",0,0,0,0,1],[2,"James Matters","b Darren Styles",12,0,0,0,0],[3,"James Piper","c Matthew Carter b Jon Harris",48,0,0,0,0],[4,"Stephen Field","c Graham Walker b Darren Styles",12,0,0,0,0],[5,"Dean Prosser","b P- Bacon",13,0,0,0,0],[6,"Lee Sugden","lbw b Tim Thirkell",15,0,0,0,0],[7,"James Harrison","run out Unsure",0,0,0,0,1],[8,"Trevor Hills","b Tim Thirkell",5,0,0,0,0],[9,"Simon Burke","run out Unsure",1,0,0,0,0],[10,"Carl Burgess","not out",4,0,0,0,0],[11,"R Studholme","b Trevor Back",8,0,0,0,0]],"bowl":[["Darren Styles","8",0,23,3,0,0],["Matthew Carter","5",0,33,0,0,0],["Jon Harris","7",0,30,1,0,0],["P- Bacon","7",3,14,1,0,0],["Tim Thirkell","4",1,8,2,0,0],["Dave Todd","3",0,9,0,0,0],["Trevor Back","2",1,1,1,0,0],["Graham Walker","1",0,2,0,0,0]],"fow":[]}],"mvp":{"Christopher Thirkell":1,"Graham Walker":4,"Matthew Carter":2,"Trevor Back":3,"Ron McCormick":6,"Tim Thirkell":4,"Mike Redman":5,"P- Bacon":4,"Darren Styles":6,"Jon Harris":2,"Dave Todd":2},"mvdh":{},"worm":null}