{"id":2292645,"date":"1999-07-17","venue":"Sheldwich Lees","comp":"Invicta League","result":"LINTON PARK CC WON BY 61 RUNS","season":1999,"home":"Sheldwich CC","away":"Linton Park CC","inns":[{"team":"Linton Park CC","total":185,"wkts":"9","overs":"46","extras":"17  (5b, 8lb, 3w, 1nb )","linton":1,"bat":[[1,"Piers McDonald","b David Prior",52,0,5,3,0],[2,"Daniel Thirkell","lbw b Richard Holland",2,0,0,0,0],[3,"Nigel Thirkell","b David Prior",31,0,4,0,0],[4,"Paul Gibson","b James Creed",2,0,0,0,0],[5,"Mike Elworthy","b James Creed",12,0,1,1,0],[6,"Stuart Cheesman","c Sam Hill b Nick Cork",21,0,2,1,0],[7,"Matt Large","c James Creed b David Knight",46,0,6,0,0],[8,"Michael Beeney","c David Knight b Nick Cork",1,0,0,0,0],[9,"Robert Quirk","c & b David Knight",0,0,0,0,1],[10,"Fred Cheesman","not out",0,0,0,0,0],[11,"Jon Harris","not out",1,0,0,0,0]],"bowl":[["John Gannon","7",1,31,0,0,0],["Richard Holland","7",1,18,1,0,0],["James Creed","12",0,53,2,0,0],["David Prior","12",5,26,2,0,0],["Nick Cork","4",0,32,2,0,0],["David Knight","4",0,12,2,0,0]],"fow":[]},{"team":"Sheldwich CC","total":124,"wkts":"9","overs":"44","extras":"11  (6b, 3lb, 2w )","linton":0,"bat":[[1,"James Creed","c Piers McDonald b Matt Large",17,0,0,0,0],[2,"David Knight","c Paul Gibson b Matt Large",3,0,0,0,0],[3,"John Gannon","b Michael Beeney",1,0,0,0,0],[4,"Steve Blythin","lbw b Jon Harris",20,0,0,0,0],[5,"David Prior","b Matt Large",24,0,0,0,0],[6,"Daniel Ray","st Piers McDonald b Jon Harris",2,0,0,0,0],[7,"Mark Hammond","not out",27,0,0,0,0],[8,"G Wright","st Piers McDonald b Jon Harris",2,0,0,0,0],[9,"Sam Hill","b Jon Harris",9,0,0,0,0],[10,"Nick Cork","b Nigel Thirkell",8,0,0,0,0],[11,"Richard Holland","not out",0,0,0,0,0]],"bowl":[["Matt Large","10",3,30,3,0,0],["Michael Beeney","9",2,11,1,0,0],["Stuart Cheesman","6",1,32,0,0,0],["Jon Harris","12",4,19,4,0,0],["Paul Gibson","4",1,16,0,0,0],["Daniel Thirkell","2",1,3,0,0,0],["Nigel Thirkell","1",0,4,1,0,0]],"fow":[]}],"mvp":{"Piers McDonald":10,"Daniel Thirkell":2,"Nigel Thirkell":3,"Paul Gibson":2,"Mike Elworthy":1,"Stuart Cheesman":2,"Matt Large":10,"Michael Beeney":4,"Robert Quirk":1,"Fred Cheesman":1,"Jon Harris":8},"mvdh":{"Robert Quirk":17},"worm":null}