{"id":2600988,"date":"1972-05-29","venue":"Linton Park","comp":null,"result":"LINTON PARK CC WON BY 131 RUNS","season":1972,"home":"Linton Park CC","away":"Bearsted CC","inns":[{"team":"Linton Park CC","total":190,"wkts":"10","overs":"57.3","extras":"4  (3b, 1lb )","linton":1,"bat":[[1,"Paul Bowles","c & b Chris Collett",58,0,6,0,0],[2,"Andrew Moss","lbw b Brian Burnett",19,0,1,0,0],[3,"Cliff Anscombe","b Chris Collett",58,0,7,1,0],[4,"Paul Brattle","b Bryan Elswood",11,0,0,0,0],[5,"John Thirkell","c Dave Bromley b Bryan Elswood",20,0,3,0,0],[6,"Nigel Thirkell","c David Andrews b Bryan Elswood",0,0,0,0,1],[7,"Dick Langridge","c Neville M Gibson b Bryan Elswood",0,0,0,0,1],[8,"Richard Ashby","not out",12,0,2,0,0],[9,"Alan Cradduck","c Denis Cleggett b Bryan Elswood",0,0,0,0,1],[10,"Ron Hickman","c Denis Cleggett b Bryan Elswood",2,0,0,0,0],[11,"Tony Gauna","c Denis Cleggett b Bryan Elswood",6,0,0,0,0]],"bowl":[["Dave Bromley","8",0,41,0,0,0],["Denis Cleggett","13",6,22,0,0,0],["Brian Burnett","13",4,44,1,0,0],["Bryan Elswood","15.3",0,57,7,0,0],["Chris Collett","7",2,19,2,0,0],["Mick Gibson","1",0,3,0,0,0]],"fow":[]},{"team":"Bearsted CC","total":59,"wkts":"10","overs":"28.3","extras":"11  (10b, 1lb )","linton":0,"bat":[[1,"Colin Fleetwood","c Cliff Anscombe b Tony Gauna",0,0,0,0,1],[2,"Neville M Gibson","b Paul Bowles",13,0,1,0,0],[3,"Denis Cleggett","c & b Paul Bowles",6,0,0,0,0],[4,"Dave Bromley","b Paul Bowles",0,0,0,0,1],[5,"Peter Court","c John Thirkell b Paul Bowles",2,0,0,0,0],[6,"Brian Burnett","b Paul Bowles",12,0,1,0,0],[7,"Bryan Elswood","b Paul Bowles",0,0,0,0,1],[8,"David Andrews","b Paul Bowles",1,0,0,0,0],[9,"P- Johnson","b Paul Bowles",13,0,1,0,0],[10,"Chris Collett","b Nigel Thirkell",0,0,0,0,1],[11,"Mick Gibson","not out",1,0,0,0,0]],"bowl":[["Tony Gauna","4",1,9,1,0,0],["Ron Hickman","6",3,9,0,0,0],["Paul Bowles","10.3",4,14,8,0,0],["Nigel Thirkell","8",2,16,1,0,0]],"fow":[[1,0,"Colin Fleetwood"],[2,24,"Denis Cleggett"],[3,24,"Dave Bromley"],[4,31,"Neville M Gibson"],[5,32,"Peter Court"],[6,34,"Bryan Elswood"],[7,50,"David Andrews"],[8,57,"Brian Burnett"],[9,57,"P- Johnson"],[10,59,"Chris Collett"]]}],"mvp":{"Paul Bowles":18,"Andrew Moss":1,"Cliff Anscombe":7,"Paul Brattle":1,"John Thirkell":3,"Nigel Thirkell":4,"Dick Langridge":1,"Richard Ashby":1,"Alan Cradduck":1,"Ron Hickman":3,"Tony Gauna":3},"mvdh":{"Nigel Thirkell":5,"Dick Langridge":5,"Alan Cradduck":5}}