{"id":2622860,"date":"1970-07-26","venue":"Linton Park","comp":null,"result":"PADDOCK WOOD CC WON BY 5 WICKETS","season":1970,"home":"Linton Park CC","away":"Paddock Wood CC","inns":[{"team":"Linton Park CC","total":61,"wkts":"10","overs":"27.1","extras":"9  (8b, 1w )","linton":1,"bat":[[1,"Andrew Moss","c C- Bird b P- Bradshaw",14,0,2,0,0],[2,"John Ames","b M- Padgham",4,0,1,0,0],[3,"Terry Whittaker","b M- Padgham",4,0,0,0,0],[4,"Richard Ashby","c K- Burr b P- Bradshaw",0,0,0,0,1],[5,"Mick Filmer","b M- Padgham",21,0,3,0,0],[6,"Dick Langridge","c K- Burr b P- Bradshaw",3,0,0,0,0],[7,"Alan Cradduck","b P- Bradshaw",0,0,0,0,1],[8,"Nigel Thirkell","b M- Padgham",2,0,0,0,0],[9,"Percy Brattle","b P- Bradshaw",0,0,0,0,1],[10,"Jon Harris","not out",2,0,0,0,0],[11,"Brian Relf","b M- Padgham",2,0,0,0,0]],"bowl":[["P- Bradshaw","14",4,27,5,0,0],["M- Padgham","13.1",3,26,5,0,0]],"fow":[]},{"team":"Paddock Wood CC","total":64,"wkts":"5","overs":"27.5","extras":"5  (5b )","linton":0,"bat":[[1,"a- Moxon","c Andrew Moss b Jon Harris",4,0,0,0,0],[2,"J- McKerracher","b John Ames",12,0,0,0,0],[3,"Mick Filmer","c Mick Filmer b Jon Harris",5,0,0,0,0],[4,"G- Matthews","b Dick Langridge",5,0,0,0,0],[5,"S- Church","c Richard Ashby b Dick Langridge",3,0,0,0,0],[6,"v- Reed","not out",22,0,0,0,0],[7,"J- Tully","not out",8,0,0,0,0]],"bowl":[["Jon Harris","12",5,24,2,0,0],["Terry Whittaker","5",2,13,0,0,0],["Dick Langridge","9.5",4,16,2,0,0],["John Ames","1",0,6,1,0,0]],"fow":[]}],"mvp":{"Andrew Moss":2,"John Ames":1,"Terry Whittaker":2,"Richard Ashby":1,"Mick Filmer":3,"Dick Langridge":4,"Alan Cradduck":0,"Nigel Thirkell":0,"Percy Brattle":0,"Jon Harris":4,"Brian Relf":0},"mvdh":{"Richard Ashby":5,"Alan Cradduck":5,"Percy Brattle":5}}