{"id":2643761,"date":"1970-09-13","venue":"Linton Park","comp":null,"result":"ABANDONED","season":1970,"home":"Linton Park CC","away":"Mersham Le Hatch CC","hl":"https://s3-eu-west-1.amazonaws.com/p-c2gallery.ecb.co.uk/uploads/website_configuration/badge_image/3970/Screenshot_2025-05-06_095716.png","al":"https://s3-eu-west-1.amazonaws.com/p-c2gallery.ecb.co.uk/uploads/website_configuration/badge_image/4299/MLHCC_Logo.jpg","toss":"Linton Park CC: Won the toss and elected to bat","wx":null,"inns":[{"team":"Linton Park CC","total":47,"wkts":"1","overs":"8","extras":"1  (1b )","linton":1,"bat":[[1,"Brian Humphries","not out",22,0,3,0,0,0,0],[2,"Paul Bowles","run out Unsure",15,0,2,0,0,0,0],[3,"David T Lowen","not out",9,0,2,0,0,0,0]],"bowl":[["R- Lewis","4",0,23,0,0,0],["W- Jeanes","1",0,8,0,0,0],["J- Smith","3",0,15,0,0,0]],"fow":[]},{"team":"Mersham Le Hatch CC","total":null,"wkts":null,"overs":null,"extras":"0","linton":0,"bat":[],"bowl":[],"fow":[]}],"mvp":{"Brian Humphries":2,"Paul Bowles":1,"David T Lowen":0},"mvdh":{}}