{"id":3225992,"date":"2018-08-05","venue":null,"comp":null,"result":"LINTON PARK CC WON BY 5 WICKETS","season":2018,"home":"Pett CC","away":"Linton Park CC","hl":"","al":"https://s3-eu-west-1.amazonaws.com/p-c2gallery.ecb.co.uk/uploads/website_configuration/badge_image/3970/Screenshot_2025-05-06_095716.png","toss":"Pett CC: Won the toss and elected to bat","wx":null,"inns":[{"team":"Pett CC","total":178,"wkts":"7","overs":"40","extras":"20  (7b, 1lb, 8w, 4nb )","linton":0,"bat":[[1,"Deluar Ahmed","c Thisal Perera b James Watkins",17,0,0,0,0,0,0],[2,"Paul Barnett","run out Shehryar Gul",25,0,0,0,0,0,0],[3,"Rob Clemence","c James Watkins b Darrell Houghton-Judge",22,0,0,0,0,0,0],[4,"Isaac Perrin","b John Karassellos",28,0,0,0,0,0,0],[5,"Chris Mills","c Richard Piper b John Karassellos",3,0,0,0,0,0,0],[6,"Parth Angre","run out Toby Hughes",18,0,0,0,0,0,0],[7,"Alex Jackson","not out",42,0,0,0,0,0,0],[8,"Alex Clayton","b Toby Hughes",0,0,0,0,1,0,0],[9,"Tanvir Ahmed","not out",3,0,0,0,0,0,0]],"bowl":[["Toby Hughes","9",0,30,1,3,0],["James Watkins","7",2,52,1,5,3],["Darrell Houghton-Judge","9",0,40,1,0,0],["Tim Thirkell","5",2,4,0,0,0],["John Karassellos","8",1,28,2,0,0],["Thisal Perera","2",0,15,0,0,1]],"fow":[[1,30,"Unsure"],[2,67,"Unsure"],[3,81,"Unsure"],[4,106,"Unsure"],[5,115,"Unsure"],[6,144,"Unsure"],[7,144,"Unsure"]]},{"team":"Linton Park CC","total":179,"wkts":"5","overs":"36.3","extras":"31  (20b, 1lb, 10w )","linton":1,"bat":[[1,"Shehryar Gul","run out Isaac Perrin",24,0,0,0,0,0,0],[2,"Richard Piper","b Deluar Ahmed",10,0,0,0,0,0,0],[3,"Charles Curteis","c Rob Clemence b Deluar Ahmed",23,0,0,0,0,0,0],[4,"Aaron Hughes","not out",59,0,0,0,0,0,1],[5,"Toby Hughes","st Paul Barnett b Elliot Upton",10,0,0,0,0,0,0],[6,"James Watkins","c Elliot Upton b Isaac Perrin",0,0,0,0,1,0,0],[7,"Darrell Houghton-Judge","not out",14,0,0,0,0,0,0]],"bowl":[["Chris Mills","5",1,42,0,0,0],["Deluar Ahmed","5",0,23,2,0,0],["Alex Clayton","8",1,26,0,0,0],["Lakshman Maheswhwaran","5",2,19,0,0,0],["Elliot Upton","6",1,18,1,0,0],["Isaac Perrin","4",0,11,1,0,0],["Tanvir Ahmed","2",0,5,0,0,0],["Parth Angre","1",0,7,0,0,0],["Rob Clemence","0.3",0,6,0,0,0]],"fow":[[1,46,"Unsure"],[2,47,"Unsure"],[3,73,"Unsure"],[4,116,"Unsure"],[5,125,"Unsure"]]}],"mvp":{"Shehryar Gul":[3,["batting +1","fielding +1","on the winning side +1"]],"Richard Piper":[2,["fielding +1","on the winning side +1"]],"Charles Curteis":[2,["batting +1","on the winning side +1"]],"Aaron Hughes":[5,["batting +4","on the winning side +1"]],"Toby Hughes":[3,["bowling +1","fielding +1","on the winning side +1"]],"James Watkins":[4,["bowling +2","fielding +1","on the winning side +1"]],"Darrell Houghton-Judge":[2,["bowling +1","on the winning side +1"]],"Tim Thirkell":[3,["bowling +2","on the winning side +1"]],"John Karassellos":[3,["bowling +2","on the winning side +1"]],"Thisal Perera":[2,["fielding +1","on the winning side +1"]]},"mvdh":{"James Watkins":[8,["duck +2","lone duck +3","home & away +3"]]}}