{"id":3268323,"date":"2018-06-16","venue":"Linton Park","comp":"KENT COUNTY VILLAGE LEAGUE","result":"FORDCOMBE CC WON BY 9 WICKETS","season":2018,"home":"Linton Park CC","away":"Fordcombe CC","inns":[{"team":"Linton Park CC","total":151,"wkts":"10","overs":"39.2","extras":"16  (7lb, 9w )","linton":1,"bat":[[1,"Jordan Austin","b Max O'Collins",29,0,4,0,0],[2,"Glen Rawson","c Richard Larkin b Keith Exton",7,0,1,0,0],[3,"Will Thew","c Max O'Collins b Alex Latter",49,0,5,0,0],[4,"Thuraiappah Pushpavinothan","c & b Keith Exton",0,0,0,0,1],[5,"Benjamin Austin","c Max O'Collins b Ashley Worcester",16,0,2,0,0],[6,"Richard Piper","run out Richard Larkin",13,0,1,0,0],[7,"Darrell Houghton-Judge","c Matt Colegate b Alex Latter",1,0,0,0,0],[8,"Stuart Campbell","c & b Max O'Collins",13,0,2,0,0],[9,"Ian Hollingworth","c Matt Colegate b Alex Latter",0,0,0,0,1],[10,"Tim Thirkell","c Matt Colegate b Keith Exton",5,0,0,0,0],[11,"Engarshal Sinnaraja","not out",2,0,0,0,0]],"bowl":[["Max O'Collins","9",0,25,2,0,0],["Matt Colegate","5",0,27,0,0,0],["Keith Exton","8.2",2,22,3,0,0],["Ashley Worcester","9",1,37,1,0,0],["Andy Garside","3",0,19,0,0,0],["Alex Latter","5",1,14,3,0,0]],"fow":[]},{"team":"Fordcombe CC","total":155,"wkts":"0","overs":"30.2","extras":"27  (7b, 1lb, 19w )","linton":0,"bat":[[1,"Keith Exton","not out",69,0,10,0,0],[2,"Richard Shackleton","not out",59,0,7,0,0]],"bowl":[["Ian Hollingworth","5",0,17,0,0,0],["Stuart Campbell","7",0,31,0,0,0],["Jordan Austin","4",0,24,0,0,0],["Tim Thirkell","7",0,24,0,0,0],["Darrell Houghton-Judge","4",0,24,0,0,0],["Engarshal Sinnaraja","2.2",0,24,0,0,0],["Will Thew","1",0,3,0,0,0]],"fow":[]}],"mvp":{"Jordan Austin":1,"Glen Rawson":0,"Will Thew":4,"Thuraiappah Pushpavinothan":0,"Benjamin Austin":0,"Richard Piper":0,"Darrell Houghton-Judge":0,"Stuart Campbell":0,"Ian Hollingworth":0,"Tim Thirkell":0,"Engarshal Sinnaraja":0},"mvdh":{"Thuraiappah Pushpavinothan":8,"Ian Hollingworth":8},"worm":null}