{"id":3306376,"date":"1989-07-28","venue":"Benenden Green","comp":"David Clark Knockout","result":"LINTON PARK CC WON BY 54 RUNS","season":1989,"home":"Benenden CC","away":"Linton Park CC","hl":"","al":"https://s3-eu-west-1.amazonaws.com/p-c2gallery.ecb.co.uk/uploads/website_configuration/badge_image/3970/Screenshot_2025-05-06_095716.png","toss":"Linton Park CC: Won the toss and elected to bat","wx":null,"inns":[{"team":"Linton Park CC","total":147,"wkts":"3","overs":"16","extras":"20  (1b, 13lb, 2w, 4nb )","linton":1,"bat":[[1,"Brian Piper","c Ray Harding b Simon Cloke",60,0,6,0,0,0,0],[2,"Nigel Thirkell","run out Unsure",63,0,4,0,0,1,0],[3,"Paul Gibson","run out Unsure",1,0,0,0,0,0,0],[4,"David Castle","not out",2,0,0,0,0,0,0],[5,"Keith Hatcher","not out",1,0,0,0,0,0,0]],"bowl":[["Mike Chambers","5",0,44,0,2,0],["Richard Wall","5",0,30,0,0,0],["Simon Cloke","5",0,48,1,0,4],["Nigel Phelps","1",0,11,0,0,0]],"fow":[[1,139,"Nigel Thirkell"],[2,143,"Brian Piper"],[3,145,"Paul Gibson"]]},{"team":"Benenden CC","total":93,"wkts":"4","overs":"16","extras":"9  (8lb, 1w )","linton":0,"bat":[[1,"Ray Harding","c David Castle b Matt Large",0,0,0,0,1,0,0],[2,"Gary Marshall","not out",45,0,3,0,0,0,0],[3,"Nick Holmes","b Matt Large",0,0,0,0,1,0,0],[4,"Andrew Cloke","b Nigel Thirkell",0,0,0,0,1,0,0],[5,"Peter Newman","c Piers McDonald b Alan Boyns",28,0,2,0,0,0,0],[6,"Simon Cloke","not out",11,0,0,0,0,0,0]],"bowl":[["Matt Large","5",0,23,2,1,0],["Nigel Thirkell","3",0,10,1,0,0],["Alan Boyns","5",0,33,1,0,0],["Jon Harris","1",0,8,0,0,0],["Paul Gibson","2",0,11,0,0,0]],"fow":[[1,0,"Ray Harding"],[2,1,"Nick Holmes"],[3,2,"Andrew Cloke"],[4,62,"Peter Newman"]]}],"mvp":{"Brian Piper":6,"Nigel Thirkell":7,"Paul Gibson":1,"David Castle":2,"Keith Hatcher":1,"Matt Large":3,"Alan Boyns":2,"Jon Harris":1,"Piers McDonald":2},"mvdh":{}}