{"id":3703128,"date":"1996-07-29","venue":"Mote CC","comp":null,"result":"MATCH DRAWN","season":1996,"home":"Linton Park CC","away":"Cleethorpes CC","inns":[{"team":"Cleethorpes CC","total":220,"wkts":"5","overs":"47","extras":"14  (3b, 5lb, 6w )","linton":0,"bat":[[1,"C Willerton","c Trevor Back b Ian Brattle",25,0,0,0,0],[2,"I Drummond","c Rob Doick b Adrian Caddick",38,0,0,0,0],[3,"Bob Leafe","b Jon Harris",73,0,0,0,0],[4,"R Green","c Rob Doick b Jon Harris",17,0,0,0,0],[5,"John Coles","not out",45,0,0,0,0],[6,"M Swain","st Rob Doick b Dave Todd",8,0,0,0,0],[7,"X Hunt","not out",0,0,0,0,0]],"bowl":[["Ian Brattle","7",0,38,1,0,0],["Darren Styles","9",1,22,0,0,0],["Jon Harris","15",2,77,2,0,0],["Adrian Caddick","7",0,43,1,0,0],["Rob Doick","7",0,26,0,0,0],["Dave Todd","2",0,6,1,0,0]],"fow":[]},{"team":"Linton Park CC","total":85,"wkts":"8","overs":"40","extras":"10  (2b, 2lb, 4w, 2nb )","linton":1,"bat":[[1,"Mike Elworthy","b Jeff Todd",3,0,0,0,0],[2,"Ron McCormick","c John Coles b C Ferrier",15,0,2,0,0],[3,"Rob Doick","c John Coles b Jeff Todd",0,0,0,0,1],[4,"Stuart Cheesman","b Tony Shepperd",5,0,1,0,0],[5,"Trevor Back","c I Drummond b Chris Quirk",8,0,2,0,0],[6,"Adam Pooley","c M Swain b Chris Quirk",3,0,0,0,0],[7,"Dave Todd","not out",19,0,2,0,0],[8,"Ian Brattle","b Chris Quirk",0,0,0,0,1],[9,"Adrian Caddick","lbw b John Coles",21,0,2,0,0],[10,"Darren Styles","not out",1,0,0,0,0]],"bowl":[["Tony Shepperd","10",4,12,1,0,0],["Jeff Todd","7",5,2,2,0,0],["Chris Quirk","5",2,7,3,0,0],["C Ferrier","8",2,28,1,0,0],["X Hunt","5",0,20,0,0,0],["John Coles","5",1,12,1,0,0]],"fow":[]}],"mvp":{"Mike Elworthy":0,"Ron McCormick":0,"Rob Doick":4,"Stuart Cheesman":0,"Trevor Back":1,"Adam Pooley":0,"Dave Todd":3,"Ian Brattle":1,"Adrian Caddick":3,"Darren Styles":1,"Jon Harris":3},"mvdh":{"Rob Doick":11,"Ian Brattle":11}}