{"id":389984,"date":"2004-08-07","venue":null,"comp":"INVICTA CRICKET LEAGUE","result":"LINTON PARK CC WON BY 3 RUNS","season":2004,"home":"Linton Park CC","away":"Milstead CC","inns":[{"team":"Linton Park CC","total":200,"wkts":"9","overs":"46","extras":"28  (12b, 16w )","linton":1,"bat":[[1,"Russell Baldwin","c Tim Fenton b Ken West",48,0,0,0,0],[2,"David Castle","b Steve Tawney",7,0,0,0,0],[3,"Daniel Thirkell","st Neil Burnop b Tim Fenton",2,0,0,0,0],[4,"Paul Gibson","b Ken West",13,0,0,0,0],[5,"Craig Sands","c Iain Rawson b Richard Moxon",20,0,0,0,0],[6,"Mike Elworthy","c & b Ken West",15,0,0,0,0],[7,"Mark Christmas","c Mike Sellar b Steve Tawney",48,0,0,0,0],[8,"Richard Knowler","c Steve Tawney b Richard Moxon",8,0,0,0,0],[9,"Dennis Salisbury","not out",7,0,0,0,0],[10,"Matt Large","b Steve Tawney",0,0,0,0,1],[11,"John Taylor","not out",4,0,0,0,0]],"bowl":[["Iain Rawson","7",0,49,0,0,0],["Steve Tawney","12",5,32,3,0,0],["Tim Fenton","3",0,25,1,0,0],["Ken West","12",2,33,3,0,0],["Richard Moxon","12",0,49,2,0,0]],"fow":[]},{"team":"Milstead CC","total":197,"wkts":"10","overs":"43.4","extras":"17  (14b, 3w )","linton":0,"bat":[[1,"Mike Sellar","run out Unsure",42,0,0,0,0],[2,"Paul West","c Mark Christmas b Daniel Thirkell",6,0,0,0,0],[3,"Richard Moxon","c Richard Knowler b Matt Large",5,0,0,0,0],[4,"Paul Carlton","lbw b Richard Knowler",66,0,0,0,0],[5,"Paul Mills","lbw b Dennis Salisbury",0,0,0,0,1],[6,"Paul Clunn","c Dennis Salisbury b Richard Knowler",8,0,0,0,0],[7,"Neil Burnop","c Daniel Thirkell b John Taylor",28,0,0,0,0],[8,"Tim Fenton","c Mark Christmas b John Taylor",16,0,0,0,0],[9,"Ken West","not out",8,0,0,0,0],[10,"Steve Tawney","b Matt Large",0,0,0,0,1],[11,"Iain Rawson","b Mark Christmas",1,0,0,0,0]],"bowl":[["Daniel Thirkell","12",2,53,1,0,0],["Matt Large","10.1",0,28,2,0,0],["Mark Christmas","1.5",0,17,1,0,0],["John Taylor","8.4",0,38,2,0,0],["Dennis Salisbury","6",0,17,1,0,0],["Richard Knowler","5",0,30,2,0,0]],"fow":[]}],"mvp":{"Russell Baldwin":4,"David Castle":1,"Daniel Thirkell":4,"Paul Gibson":1,"Craig Sands":2,"Mike Elworthy":1,"Mark Christmas":7,"Richard Knowler":4,"Dennis Salisbury":4,"Matt Large":4,"John Taylor":3},"mvdh":{"Matt Large":8}}