{"id":499024,"date":"2011-06-05","venue":"Tyler Hill Recreation Ground","comp":null,"result":"ABANDONED","season":2011,"home":"Tyler Hill CC","away":"Linton Park CC","inns":[{"team":"Linton Park CC","total":79,"wkts":"0","overs":"12","extras":"6  (1b, 2lb, 3w )","linton":1,"bat":[[1,"Richard Piper","not out",49,45,10,0,0],[2,"Mark Christmas","not out",24,27,5,0,0]],"bowl":[["Ben King","3",0,31,0,3,0],["A Pritesh","6",2,32,0,0,0],["Karl Sutcliffe","3",0,13,0,0,0]],"fow":[]},{"team":"Tyler Hill CC","total":null,"wkts":null,"overs":null,"extras":"0","linton":0,"bat":[],"bowl":[],"fow":[]}],"mvp":{"Richard Piper":4,"Mark Christmas":2},"mvdh":{}}