{"id":6357025,"date":"2024-06-11","venue":null,"comp":null,"result":"Rainham (Kent) CC Under 17 131/4 def. Linton Park CC Under 17 99/7","season":2024,"home":"Rainham (Kent) CC Under 17","away":"Linton Park CC Under 17","hl":"","al":"","toss":"","wx":null,"inns":[{"team":"Rainham (Kent) CC","total":null,"wkts":null,"overs":null,"extras":null,"linton":0,"bat":[[1,"Liam Evans","b A Nunn",0,5,0,0,1,0,0],[2,"Jamie Foden","b H Campbell",26,27,3,0,0,0,0],[3,"Lucas Harle","no",55,44,6,0,0,0,0],[4,"Z Leigh","b H Campbell",9,8,0,0,0,0,0],[5,"A Shabu","c E Beardwell b P Swart",12,11,0,1,0,0,0],[6,"H Pardesi","no",1,2,0,0,0,0,0]],"bowl":[["P Swart","4.1",0,19,1,6,0],["Oliver Bettles","1",0,14,0,0,0],["Alexander Nunn","3",0,24,1,4,1],["M Boxer","2",0,13,0,4,0],["Reuben Mundell","2",0,18,0,0,1],["H Campbell","3",0,21,2,2,0],["Johan Eloff","1",0,15,0,3,0]],"dnb":[["Elliot Jarrett",0,0],["Samuel Foote",0,0],["Jack Doust",0,0],["Joseph Egan",0,0],["Nathan Cunliffe",0,0]],"fow":[]},{"team":"Linton Park CC","total":null,"wkts":null,"overs":null,"extras":null,"linton":1,"bat":[[1,"P Swart","c Z Leigh b J Egan",13,10,3,0,0,0,0],[2,"Theo Clements","lbw  b A Shabu",26,34,4,0,0,0,1],[3,"H Campbell","c L Evans b S Foote",0,3,0,0,1,0,0],[4,"M Boxer","b N Cunliffe",11,20,0,1,0,0,0],[5,"Alexander Nunn","ro (L Evans)",2,10,0,0,0,0,0],[6,"Reuben Mundell","ro (Z Leigh)",4,7,0,0,0,0,0],[7,"Johan Eloff","b Z Leigh",0,1,0,0,1,0,0],[8,"Thomas Mundell","no",7,8,1,0,0,0,0],[9,"Oliver Bettles","no",6,6,1,0,0,0,0]],"bowl":[["Samuel Foote","3",2,9,1,0,0],["Joseph Egan","3",0,29,1,13,3],["Nathan Cunliffe","3",0,15,1,5,0],["A Shabu","3",0,20,1,1,0],["H Pardesi","2",0,6,0,0,0],["Z Leigh","2",0,15,1,3,0]],"dnb":[["Alfie Marples",0,0],["E Beardwell",0,0]],"fow":[]}],"mvp":{},"mvdh":{},"worm":[[[1,9,0],[2,22,1],[3,22,2],[4,35,2],[5,35,2],[6,38,2],[7,48,2],[8,55,2],[9,58,3],[10,63,3],[11,68,3],[12,77,4],[13,81,4],[14,85,7],[15,87,7],[16,99,7]],[[1,7,0],[2,21,0],[3,25,1],[4,30,1],[5,42,1],[6,51,1],[7,59,1],[8,65,1],[9,71,1],[10,83,1],[11,93,2],[12,100,2],[13,106,3],[14,112,3],[15,127,3],[16,131,4]]],"balls":[[{"ov":1,"bowl":"S Foote","t":["\u2022","4","\u2022","\u2022","4","1"],"sc":[[0,0],[4,0],[4,0],[4,0],[8,0],[9,0]],"wd":[null,null,null,null,null,null],"bs":[["P Swart",0,1,0,0,0.0],["P Swart",4,2,1,0,200.0],["P Swart",4,3,1,0,133.3],["P Swart",4,4,1,0,100.0],["P Swart",8,5,2,0,160.0],["P Swart",9,6,2,0,150.0]],"sh":[null,[135.9,56.0,4],null,null,[217.7,59.7,4],[133.7,37.7,1]],"cm":["0.1 S Foote to P Swart, no run","0.2 S Foote to P Swart, <b>FOUR</b>, driven over mid-on","0.3 S Foote to P Swart, no run","0.4 S Foote to P Swart, no run","0.5 S Foote to P Swart, <b>FOUR</b>, driven wide of mid-off","0.6 S Foote to P Swart, 1 run, clipped through mid-wicket"],"runs":9,"wkts":0,"rt":9},{"ov":2,"bowl":"J Egan","t":["\u2022","\u2022","wd5","4","W","1nb","wd","wd2","\u2022","\u2022"],"sc":[[9,0],[9,0],[14,0],[18,0],[18,1],[19,1],[20,1],[22,1],[22,1],[22,1]],"wd":[null,null,null,null,{"o":"P Swart","oab":"P Swart","od":"c Z Leigh b J Egan","or":13,"ob":10,"o4":3,"o6":0,"osr":null,"n":null,"nr":null,"nb":null,"n4":null,"n6":null,"nsr":null},null,null,null,null,null],"bs":[["P Swart",9,7,2,0,128.6],["P Swart",9,8,2,0,112.5],["P Swart",9,9,2,0,100.0],["P Swart",13,10,3,0,130.0],["P Swart",13,11,3,0,118.2],["H Campbell",0,1,0,0,0.0],["H Campbell",0,2,0,0,0.0],["H Campbell",0,3,0,0,0.0],["Theo Clements",0,1,0,0,0.0],["Theo Clements",0,2,0,0,0.0]],"sh":[null,null,null,[153.6,57.8,4],null,null,null,null,null,null],"cm":["1.1 J Egan to P Swart, no run","1.2 J Egan to P Swart, no run","1.3 J Egan to P Swart, no run","1.4 J Egan to P Swart, <b>FOUR</b>, driven over mid-on","1.5 J Egan to P Swart, <b>OUT!</b> c Z Leigh b J Egan","1.6 J Egan to H Campbell, no run","1.7 J Egan to H Campbell, no run","1.8 J Egan to H Campbell, no run","1.9 J Egan to T Clements, no run","1.10 J Egan to T Clements, no run"],"runs":13,"wkts":1,"rt":22},{"ov":3,"bowl":"S Foote","t":["\u2022","W","\u2022","\u2022","\u2022","\u2022"],"sc":[[22,1],[22,2],[22,2],[22,2],[22,2],[22,2]],"wd":[null,{"o":"H Campbell","oab":"H Campbell","od":"c L Evans b S Foote","or":0,"ob":3,"o4":0,"o6":0,"osr":null,"n":"Theo Clements","nr":0,"nb":2,"n4":0,"n6":0,"nsr":0.0},null,null,null,null],"bs":[["H Campbell",0,4,0,0,0.0],["H Campbell",0,5,0,0,0.0],["M Boxer",0,1,0,0,0.0],["M Boxer",0,2,0,0,0.0],["M Boxer",0,3,0,0,0.0],["M Boxer",0,4,0,0,0.0]],"sh":[null,null,null,null,null,null],"cm":["2.1 S Foote to H Campbell, no run","2.2 S Foote to H Campbell, <b>OUT!</b> c L Evans b S Foote","2.3 S Foote to M Boxer, no run","2.4 S Foote to M Boxer, no run","2.5 S Foote to M Boxer, no run","2.6 S Foote to M Boxer, no run"],"runs":0,"wkts":1,"rt":22},{"ov":4,"bowl":"J Egan","t":["\u2022","wd2","wd","wd2","4","\u2022","\u2022","3nb","\u2022","1"],"sc":[[22,2],[24,2],[25,2],[27,2],[31,2],[31,2],[31,2],[34,2],[34,2],[35,2]],"wd":[null,null,null,null,null,null,null,null,null,null],"bs":[["Theo Clements",0,3,0,0,0.0],["Theo Clements",0,4,0,0,0.0],["M Boxer",0,5,0,0,0.0],["M Boxer",0,6,0,0,0.0],["Theo Clements",4,5,1,0,80.0],["Theo Clements",4,6,1,0,66.7],["Theo Clements",4,7,1,0,57.1],["Theo Clements",6,8,1,0,75.0],["Theo Clements",6,9,1,0,66.7],["Theo Clements",7,10,1,0,70.0]],"sh":[null,null,null,null,[66.7,43.6,4],null,null,[266.4,40.1,2],null,[312.9,26.8,1]],"cm":["3.1 J Egan to T Clements, no run","3.2 J Egan to T Clements, no run","3.3 J Egan to M Boxer, no run","3.4 J Egan to M Boxer, no run","3.5 J Egan to T Clements, <b>FOUR</b>, pulled backward of square","3.6 J Egan to T Clements, no run","3.7 J Egan to T Clements, no run","3.8 J Egan to T Clements, 2 runs, cut square on the off side","3.9 J Egan to T Clements, no run","3.10 J Egan to T Clements, 1 run, edged through the gully"],"runs":13,"wkts":0,"rt":35},{"ov":5,"bowl":"S Foote","t":["\u2022","\u2022","\u2022","\u2022","\u2022","\u2022"],"sc":[[35,2],[35,2],[35,2],[35,2],[35,2],[35,2]],"wd":[null,null,null,null,null,null],"bs":[["Theo Clements",7,11,1,0,63.6],["Theo Clements",7,12,1,0,58.3],["Theo Clements",7,13,1,0,53.8],["Theo Clements",7,14,1,0,50.0],["Theo Clements",7,15,1,0,46.7],["Theo Clements",7,16,1,0,43.8]],"sh":[null,null,null,null,null,null],"cm":["4.1 S Foote to T Clements, no run","4.2 S Foote to T Clements, no run","4.3 S Foote to T Clements, no run","4.4 S Foote to T Clements, no run","4.5 S Foote to T Clements, no run","4.6 S Foote to T Clements, no run"],"runs":0,"wkts":0,"rt":35},{"ov":6,"bowl":"J Egan","t":["\u2022","\u2022","2","\u2022","1nb","\u2022","\u2022"],"sc":[[35,2],[35,2],[37,2],[37,2],[38,2],[38,2],[38,2]],"wd":[null,null,null,null,null,null,null],"bs":[["M Boxer",0,7,0,0,0.0],["M Boxer",0,8,0,0,0.0],["M Boxer",2,9,0,0,22.2],["M Boxer",2,10,0,0,20.0],["M Boxer",2,11,0,0,18.2],["M Boxer",2,12,0,0,16.7],["M Boxer",2,13,0,0,15.4]],"sh":[null,null,[307.1,37.1,2],null,null,null,null],"cm":["5.1 J Egan to M Boxer, no run","5.2 J Egan to M Boxer, no run","5.3 J Egan to M Boxer, 2 runs, edged through the gully","5.4 J Egan to M Boxer, no run","5.5 J Egan to M Boxer, no run","5.6 J Egan to M Boxer, no run","5.7 J Egan to M Boxer, no run"],"runs":3,"wkts":0,"rt":38},{"ov":7,"bowl":"N Cunliffe","t":["1","wd","6","\u2022","2","\u2022","\u2022"],"sc":[[39,2],[40,2],[46,2],[46,2],[48,2],[48,2],[48,2]],"wd":[null,null,null,null,null,null,null],"bs":[["Theo Clements",8,17,1,0,47.1],["M Boxer",2,14,0,0,14.3],["M Boxer",8,15,0,1,53.3],["M Boxer",8,16,0,1,50.0],["M Boxer",10,17,0,1,58.8],["M Boxer",10,18,0,1,55.6],["M Boxer",10,19,0,1,52.6]],"sh":[[123.6,44.3,1],null,[245.5,51.5,6],null,[261.6,42.8,2],null,null],"cm":["6.1 N Cunliffe to T Clements, 1 run, clipped through mid-wicket","6.2 N Cunliffe to M Boxer, no run","6.3 N Cunliffe to M Boxer, <b>SIX</b>, launched through extra cover","6.4 N Cunliffe to M Boxer, no run","6.5 N Cunliffe to M Boxer, 2 runs, cut square on the off side","6.6 N Cunliffe to M Boxer, no run","6.7 N Cunliffe to M Boxer, no run"],"runs":10,"wkts":0,"rt":48},{"ov":8,"bowl":"A Shabu","t":["4","\u2022","1","1","1","\u2022"],"sc":[[52,2],[52,2],[53,2],[54,2],[55,2],[55,2]],"wd":[null,null,null,null,null,null],"bs":[["Theo Clements",12,18,2,0,66.7],["Theo Clements",12,19,2,0,63.2],["Theo Clements",13,20,2,0,65.0],["M Boxer",11,20,0,1,55.0],["Theo Clements",14,21,2,0,66.7],["M Boxer",11,21,0,1,52.4]],"sh":[[228.4,56.9,4],null,[154.6,39.3,1],[273.7,33.8,1],[251.8,39.0,1],null],"cm":["7.1 A Shabu to T Clements, <b>FOUR</b>, driven through extra cover","7.2 A Shabu to T Clements, no run","7.3 A Shabu to T Clements, 1 run, driven over mid-on","7.4 A Shabu to M Boxer, 1 run, cut square on the off side","7.5 A Shabu to T Clements, 1 run, driven through extra cover","7.6 A Shabu to M Boxer, no run"],"runs":7,"wkts":0,"rt":55},{"ov":9,"bowl":"N Cunliffe","t":["1b","\u2022","wd","W","\u2022","\u2022","1lb"],"sc":[[56,2],[56,2],[57,2],[57,3],[57,3],[57,3],[58,3]],"wd":[null,null,null,{"o":"M Boxer","oab":"M Boxer","od":"b N Cunliffe","or":11,"ob":20,"o4":0,"o6":1,"osr":null,"n":"Theo Clements","nr":14,"nb":22,"n4":2,"n6":0,"nsr":63.6},null,null,null],"bs":[["Theo Clements",14,22,2,0,63.6],["M Boxer",11,22,0,1,50.0],["M Boxer",11,23,0,1,47.8],["M Boxer",11,24,0,1,45.8],["Alexander Nunn",0,1,0,0,0.0],["Alexander Nunn",0,2,0,0,0.0],["Alexander Nunn",0,3,0,0,0.0]],"sh":[null,null,null,null,null,null,null],"cm":["8.1 N Cunliffe to T Clements, no run","8.2 N Cunliffe to M Boxer, no run","8.3 N Cunliffe to M Boxer, no run","8.4 N Cunliffe to M Boxer, <b>OUT!</b> b N Cunliffe","8.5 N Cunliffe to A Nunn, no run","8.6 N Cunliffe to A Nunn, no run","8.7 N Cunliffe to A Nunn, no run"],"runs":3,"wkts":1,"rt":58},{"ov":10,"bowl":"A Shabu","t":["1","\u2022","4","\u2022","\u2022","\u2022"],"sc":[[59,3],[59,3],[63,3],[63,3],[63,3],[63,3]],"wd":[null,null,null,null,null,null],"bs":[["Alexander Nunn",1,4,0,0,25.0],["Theo Clements",14,23,2,0,60.9],["Theo Clements",18,24,3,0,75.0],["Theo Clements",18,25,3,0,72.0],["Theo Clements",18,26,3,0,69.2],["Theo Clements",18,27,3,0,66.7]],"sh":[[307.3,28.1,1],null,[103.9,48.9,4],null,null,null],"cm":["9.1 A Shabu to A Nunn, 1 run, edged through the gully","9.2 A Shabu to T Clements, no run","9.3 A Shabu to T Clements, <b>FOUR</b>, pulled square on the leg side","9.4 A Shabu to T Clements, no run","9.5 A Shabu to T Clements, no run","9.6 A Shabu to T Clements, no run"],"runs":5,"wkts":0,"rt":63},{"ov":11,"bowl":"N Cunliffe","t":["1lb","wd","\u2022","\u2022","\u2022","1","wd","wd","\u2022"],"sc":[[64,3],[65,3],[65,3],[65,3],[65,3],[66,3],[67,3],[68,3],[68,3]],"wd":[null,null,null,null,null,null,null,null,null],"bs":[["Alexander Nunn",1,5,0,0,20.0],["Theo Clements",18,28,3,0,64.3],["Theo Clements",18,29,3,0,62.1],["Theo Clements",18,30,3,0,60.0],["Theo Clements",18,31,3,0,58.1],["Theo Clements",19,32,3,0,59.4],["Alexander Nunn",1,6,0,0,16.7],["Alexander Nunn",1,7,0,0,14.3],["Alexander Nunn",1,8,0,0,12.5]],"sh":[null,null,null,null,null,[230.2,30.4,1],null,null,null],"cm":["10.1 N Cunliffe to A Nunn, no run","10.2 N Cunliffe to T Clements, no run","10.3 N Cunliffe to T Clements, no run","10.4 N Cunliffe to T Clements, no run","10.5 N Cunliffe to T Clements, no run","10.6 N Cunliffe to T Clements, 1 run, driven through extra cover","10.7 N Cunliffe to A Nunn, no run","10.8 N Cunliffe to A Nunn, no run","10.9 N Cunliffe to A Nunn, no run"],"runs":5,"wkts":0,"rt":68},{"ov":12,"bowl":"A Shabu","t":["1","1lb","wd","2","4","W","\u2022"],"sc":[[69,3],[70,3],[71,3],[73,3],[77,3],[77,4],[77,4]],"wd":[null,null,null,null,null,{"o":"Theo Clements","oab":"T Clements","od":"lbw  b A Shabu","or":26,"ob":34,"o4":4,"o6":0,"osr":null,"n":"Alexander Nunn","nr":1,"nb":9,"n4":0,"n6":0,"nsr":11.1},null],"bs":[["Theo Clements",20,33,3,0,60.6],["Alexander Nunn",1,9,0,0,11.1],["Theo Clements",20,34,3,0,58.8],["Theo Clements",22,35,3,0,62.9],["Theo Clements",26,36,4,0,72.2],["Theo Clements",26,37,4,0,70.3],["Reuben Mundell",0,1,0,0,0.0]],"sh":[[216.1,39.3,1],null,null,[160.7,45.7,2],[215.6,58.9,4],null,null],"cm":["11.1 A Shabu to T Clements, 1 run, driven wide of mid-off","11.2 A Shabu to A Nunn, no run","11.3 A Shabu to T Clements, no run","11.4 A Shabu to T Clements, 2 runs, driven over mid-on","11.5 A Shabu to T Clements, <b>FOUR</b>, driven wide of mid-off","11.6 A Shabu to T Clements, <b>OUT!</b> lbw  b A Shabu","11.7 A Shabu to R Mundell, no run"],"runs":9,"wkts":1,"rt":77},{"ov":13,"bowl":"H Pardesi","t":["\u2022","1","\u2022","\u2022","2","1"],"sc":[[77,4],[78,4],[78,4],[78,4],[80,4],[81,4]],"wd":[null,null,null,null,null,null],"bs":[["Alexander Nunn",1,10,0,0,10.0],["Alexander Nunn",2,11,0,0,18.2],["Reuben Mundell",0,2,0,0,0.0],["Reuben Mundell",0,3,0,0,0.0],["Reuben Mundell",2,4,0,0,50.0],["Reuben Mundell",3,5,0,0,60.0]],"sh":[null,[140.0,32.0,1],null,null,[94.9,36.8,2],[275.7,29.6,1]],"cm":["12.1 H Pardesi to A Nunn, no run","12.2 H Pardesi to A Nunn, 1 run, driven over mid-on","12.3 H Pardesi to R Mundell, no run","12.4 H Pardesi to R Mundell, no run","12.5 H Pardesi to R Mundell, 2 runs, pulled square on the leg side","12.6 H Pardesi to R Mundell, 1 run, cut square on the off side"],"runs":4,"wkts":0,"rt":81},{"ov":14,"bowl":"Z Leigh","t":["1","W","W","1","wd","W","wd","\u2022"],"sc":[[82,4],[82,5],[82,6],[83,6],[84,6],[84,7],[85,7],[85,7]],"wd":[null,{"o":"Alexander Nunn","oab":"A Nunn","od":"ro (L Evans)","or":2,"ob":10,"o4":0,"o6":0,"osr":null,"n":"Reuben Mundell","nr":4,"nb":6,"n4":0,"n6":0,"nsr":66.7},{"o":"Johan Eloff","oab":"J Eloff","od":"b Z Leigh","or":0,"ob":1,"o4":0,"o6":0,"osr":null,"n":"Reuben Mundell","nr":4,"nb":6,"n4":0,"n6":0,"nsr":66.7},null,null,{"o":"Reuben Mundell","oab":"R Mundell","od":"ro (Z Leigh)","or":4,"ob":7,"o4":0,"o6":0,"osr":null,"n":"Thomas Mundell","nr":1,"nb":1,"n4":0,"n6":0,"nsr":100.0},null,null],"bs":[["Reuben Mundell",4,6,0,0,66.7],["Alexander Nunn",2,12,0,0,16.7],["Johan Eloff",0,1,0,0,0.0],["Thomas Mundell",1,1,0,0,100.0],["Reuben Mundell",4,7,0,0,57.1],["Reuben Mundell",4,8,0,0,50.0],["Oliver Bettles",0,1,0,0,0.0],["Oliver Bettles",0,2,0,0,0.0]],"sh":[[142.2,33.0,1],null,null,[203.6,41.7,1],null,null,null,null],"cm":["13.1 Z Leigh to R Mundell, 1 run, driven over mid-on","13.2 Z Leigh to A Nunn, <b>OUT!</b> ro (L Evans)","13.3 Z Leigh to J Eloff, <b>OUT!</b> b Z Leigh","13.4 Z Leigh to T Mundell, 1 run, driven wide of mid-off","13.5 Z Leigh to R Mundell, no run","13.6 Z Leigh to R Mundell, <b>OUT!</b> ro (Z Leigh)","13.7 Z Leigh to O Bettles, no run","13.8 Z Leigh to O Bettles, no run"],"runs":4,"wkts":3,"rt":85},{"ov":15,"bowl":"H Pardesi","t":["\u2022","\u2022","1","\u2022","1","\u2022"],"sc":[[85,7],[85,7],[86,7],[86,7],[87,7],[87,7]],"wd":[null,null,null,null,null,null],"bs":[["Thomas Mundell",1,2,0,0,50.0],["Thomas Mundell",1,3,0,0,33.3],["Thomas Mundell",2,4,0,0,50.0],["Oliver Bettles",0,3,0,0,0.0],["Oliver Bettles",1,4,0,0,25.0],["Thomas Mundell",2,5,0,0,40.0]],"sh":[null,null,[221.2,39.9,1],null,[321.9,29.9,1],null],"cm":["14.1 H Pardesi to T Mundell, no run","14.2 H Pardesi to T Mundell, no run","14.3 H Pardesi to T Mundell, 1 run, driven wide of mid-off","14.4 H Pardesi to O Bettles, no run","14.5 H Pardesi to O Bettles, 1 run, steered down to third man","14.6 H Pardesi to T Mundell, no run"],"runs":2,"wkts":0,"rt":87},{"ov":16,"bowl":"Z Leigh","t":["wd","1b","\u2022","1","4","1","4"],"sc":[[88,7],[89,7],[89,7],[90,7],[94,7],[95,7],[99,7]],"wd":[null,null,null,null,null,null,null],"bs":[["Oliver Bettles",1,5,0,0,20.0],["Oliver Bettles",1,6,0,0,16.7],["Thomas Mundell",2,6,0,0,33.3],["Thomas Mundell",3,7,0,0,42.9],["Oliver Bettles",5,7,1,0,71.4],["Oliver Bettles",6,8,1,0,75.0],["Thomas Mundell",7,8,1,0,87.5]],"sh":[null,null,null,[205.4,42.5,1],[225.8,56.9,4],[162.3,42.0,1],[154.0,58.7,4]],"cm":["15.1 Z Leigh to O Bettles, no run","15.2 Z Leigh to O Bettles, no run","15.3 Z Leigh to T Mundell, no run","15.4 Z Leigh to T Mundell, 1 run, driven wide of mid-off","15.5 Z Leigh to O Bettles, <b>FOUR</b>, driven through extra cover","15.6 Z Leigh to O Bettles, 1 run, driven over mid-on","15.7 Z Leigh to T Mundell, <b>FOUR</b>, driven over mid-on"],"runs":12,"wkts":0,"rt":99}],[{"ov":1,"bowl":"P Swart","t":["\u2022","\u2022","wd5","1lb","\u2022","1lb","\u2022"],"sc":[[0,0],[0,0],[5,0],[6,0],[6,0],[7,0],[7,0]],"wd":[null,null,null,null,null,null,null],"bs":[["Liam Evans",0,1,0,0,0.0],["Liam Evans",0,2,0,0,0.0],["Liam Evans",0,3,0,0,0.0],["Liam Evans",0,4,0,0,0.0],["Jamie Foden",0,1,0,0,0.0],["Jamie Foden",0,2,0,0,0.0],["Liam Evans",0,5,0,0,0.0]],"sh":[null,null,null,null,null,null,null],"cm":["0.1 P Swart to L Evans, no run","0.2 P Swart to L Evans, no run","0.3 P Swart to L Evans, no run","0.4 P Swart to L Evans, no run","0.5 P Swart to J Foden, no run","0.6 P Swart to J Foden, no run","0.7 P Swart to L Evans, no run"],"runs":7,"wkts":0,"rt":7},{"ov":2,"bowl":"O Bettles","t":["2","4","\u2022","4","4","\u2022"],"sc":[[9,0],[13,0],[13,0],[17,0],[21,0],[21,0]],"wd":[null,null,null,null,null,null],"bs":[["Jamie Foden",2,3,0,0,66.7],["Jamie Foden",6,4,1,0,150.0],["Jamie Foden",6,5,1,0,120.0],["Jamie Foden",10,6,2,0,166.7],["Jamie Foden",14,7,3,0,200.0],["Jamie Foden",14,8,3,0,175.0]],"sh":[[268.4,42.8,2],[97.0,51.4,4],null,[98.1,50.3,4],[106.9,51.9,4],null],"cm":["1.1 O Bettles to J Foden, 2 runs, cut square on the off side","1.2 O Bettles to J Foden, <b>FOUR</b>, pulled square on the leg side","1.3 O Bettles to J Foden, no run","1.4 O Bettles to J Foden, <b>FOUR</b>, pulled square on the leg side","1.5 O Bettles to J Foden, <b>FOUR</b>, clipped through mid-wicket","1.6 O Bettles to J Foden, no run"],"runs":14,"wkts":0,"rt":21},{"ov":3,"bowl":"A Nunn","t":["W","wd","\u2022","\u2022","1","\u2022","2"],"sc":[[21,1],[22,1],[22,1],[22,1],[23,1],[23,1],[25,1]],"wd":[{"o":"Liam Evans","oab":"L Evans","od":"b A Nunn","or":0,"ob":5,"o4":0,"o6":0,"osr":null,"n":"Jamie Foden","nr":14,"nb":8,"n4":3,"n6":0,"nsr":175.0},null,null,null,null,null,null],"bs":[["Liam Evans",0,6,0,0,0.0],["Lucas Harle",0,1,0,0,0.0],["Lucas Harle",0,2,0,0,0.0],["Lucas Harle",0,3,0,0,0.0],["Lucas Harle",1,4,0,0,25.0],["Jamie Foden",14,9,3,0,155.6],["Jamie Foden",16,10,3,0,160.0]],"sh":[null,null,null,null,[151.3,41.6,1],null,[207.7,46.7,2]],"cm":["2.1 A Nunn to L Evans, <b>OUT!</b> b A Nunn","2.2 A Nunn to L Harle, no run","2.3 A Nunn to L Harle, no run","2.4 A Nunn to L Harle, no run","2.5 A Nunn to L Harle, 1 run, driven over mid-on","2.6 A Nunn to J Foden, no run","2.7 A Nunn to J Foden, 2 runs, driven wide of mid-off"],"runs":4,"wkts":1,"rt":25},{"ov":4,"bowl":"M Boxer","t":["\u2022","\u2022","\u2022","\u2022","wd","4","\u2022"],"sc":[[25,1],[25,1],[25,1],[25,1],[26,1],[30,1],[30,1]],"wd":[null,null,null,null,null,null,null],"bs":[["Lucas Harle",1,5,0,0,20.0],["Lucas Harle",1,6,0,0,16.7],["Lucas Harle",1,7,0,0,14.3],["Lucas Harle",1,8,0,0,12.5],["Lucas Harle",1,9,0,0,11.1],["Lucas Harle",5,10,1,0,50.0],["Lucas Harle",5,11,1,0,45.5]],"sh":[null,null,null,null,null,[292.1,48.0,4],null],"cm":["3.1 M Boxer to L Harle, no run","3.2 M Boxer to L Harle, no run","3.3 M Boxer to L Harle, no run","3.4 M Boxer to L Harle, no run","3.5 M Boxer to L Harle, no run","3.6 M Boxer to L Harle, <b>FOUR</b>, edged through the gully","3.7 M Boxer to L Harle, no run"],"runs":5,"wkts":0,"rt":30},{"ov":5,"bowl":"A Nunn","t":["1","4","1","\u2022","1","wd","4"],"sc":[[31,1],[35,1],[36,1],[36,1],[37,1],[38,1],[42,1]],"wd":[null,null,null,null,null,null,null],"bs":[["Jamie Foden",17,11,3,0,154.5],["Lucas Harle",9,12,2,0,75.0],["Lucas Harle",10,13,2,0,76.9],["Jamie Foden",17,12,3,0,141.7],["Jamie Foden",18,13,3,0,138.5],["Lucas Harle",10,14,2,0,71.4],["Lucas Harle",14,15,3,0,93.3]],"sh":[[204.6,37.7,1],[258.7,51.0,4],[317.5,28.2,1],null,[126.1,34.9,1],null,[197.8,57.0,4]],"cm":["4.1 A Nunn to J Foden, 1 run, driven wide of mid-off","4.2 A Nunn to L Harle, <b>FOUR</b>, cut square on the off side","4.3 A Nunn to L Harle, 1 run, edged through the gully","4.4 A Nunn to J Foden, no run","4.5 A Nunn to J Foden, 1 run, clipped through mid-wicket","4.6 A Nunn to L Harle, no run","4.7 A Nunn to L Harle, <b>FOUR</b>, driven wide of mid-off"],"runs":12,"wkts":0,"rt":42},{"ov":6,"bowl":"M Boxer","t":["wd2","1lb","\u2022","wd","1","2","2","\u2022"],"sc":[[44,1],[45,1],[45,1],[46,1],[47,1],[49,1],[51,1],[51,1]],"wd":[null,null,null,null,null,null,null,null],"bs":[["Jamie Foden",18,14,3,0,128.6],["Lucas Harle",14,16,3,0,87.5],["Jamie Foden",18,15,3,0,120.0],["Jamie Foden",18,16,3,0,112.5],["Jamie Foden",19,17,3,0,111.8],["Lucas Harle",16,17,3,0,94.1],["Lucas Harle",18,18,3,0,100.0],["Lucas Harle",18,19,3,0,94.7]],"sh":[null,null,null,null,[133.7,38.0,1],[293.7,36.6,2],[256.4,43.4,2],null],"cm":["5.1 M Boxer to J Foden, no run","5.2 M Boxer to L Harle, no run","5.3 M Boxer to J Foden, no run","5.4 M Boxer to J Foden, no run","5.5 M Boxer to J Foden, 1 run, clipped through mid-wicket","5.6 M Boxer to L Harle, 2 runs, edged through the gully","5.7 M Boxer to L Harle, 2 runs, cut square on the off side","5.8 M Boxer to L Harle, no run"],"runs":9,"wkts":0,"rt":51},{"ov":7,"bowl":"A Nunn","t":["wd","2","1","1","\u2022","wd","\u2022","1nb","1"],"sc":[[52,1],[54,1],[55,1],[56,1],[56,1],[57,1],[57,1],[58,1],[59,1]],"wd":[null,null,null,null,null,null,null,null,null],"bs":[["Jamie Foden",19,18,3,0,105.6],["Jamie Foden",21,19,3,0,110.5],["Jamie Foden",22,20,3,0,110.0],["Lucas Harle",19,20,3,0,95.0],["Jamie Foden",22,21,3,0,104.8],["Jamie Foden",22,22,3,0,100.0],["Jamie Foden",22,23,3,0,95.7],["Jamie Foden",22,24,3,0,91.7],["Jamie Foden",23,25,3,0,92.0]],"sh":[null,[93.9,45.6,2],[144.1,40.2,1],[124.1,37.4,1],null,null,null,null,[226.4,35.2,1]],"cm":["6.1 A Nunn to J Foden, no run","6.2 A Nunn to J Foden, 2 runs, pulled square on the leg side","6.3 A Nunn to J Foden, 1 run, driven over mid-on","6.4 A Nunn to L Harle, 1 run, clipped through mid-wicket","6.5 A Nunn to J Foden, no run","6.6 A Nunn to J Foden, no run","6.7 A Nunn to J Foden, no run","6.8 A Nunn to J Foden, no run","6.9 A Nunn to J Foden, 1 run, driven through extra cover"],"runs":8,"wkts":0,"rt":59},{"ov":8,"bowl":"R Mundell","t":["\u2022","1","4","\u2022","\u2022","1"],"sc":[[59,1],[60,1],[64,1],[64,1],[64,1],[65,1]],"wd":[null,null,null,null,null,null],"bs":[["Jamie Foden",23,26,3,0,88.5],["Jamie Foden",24,27,3,0,88.9],["Lucas Harle",23,21,4,0,109.5],["Lucas Harle",23,22,4,0,104.5],["Lucas Harle",23,23,4,0,100.0],["Lucas Harle",24,24,4,0,100.0]],"sh":[null,[218.5,43.1,1],[202.0,59.6,4],null,null,[68.4,26.1,1]],"cm":["7.1 R Mundell to J Foden, no run","7.2 R Mundell to J Foden, 1 run, driven wide of mid-off","7.3 R Mundell to L Harle, <b>FOUR</b>, driven wide of mid-off","7.4 R Mundell to L Harle, no run","7.5 R Mundell to L Harle, no run","7.6 R Mundell to L Harle, 1 run, pulled backward of square"],"runs":6,"wkts":0,"rt":65},{"ov":9,"bowl":"H Campbell","t":["2","1","\u2022","1","\u2022","2"],"sc":[[67,1],[68,1],[68,1],[69,1],[69,1],[71,1]],"wd":[null,null,null,null,null,null],"bs":[["Lucas Harle",26,25,4,0,104.0],["Lucas Harle",27,26,4,0,103.8],["Jamie Foden",24,28,3,0,85.7],["Jamie Foden",25,29,3,0,86.2],["Lucas Harle",27,27,4,0,100.0],["Lucas Harle",29,28,4,0,103.6]],"sh":[[103.5,42.1,2],[133.7,36.3,1],null,[213.2,40.8,1],null,[115.5,40.6,2]],"cm":["8.1 H Campbell to L Harle, 2 runs, pulled square on the leg side","8.2 H Campbell to L Harle, 1 run, clipped through mid-wicket","8.3 H Campbell to J Foden, no run","8.4 H Campbell to J Foden, 1 run, driven wide of mid-off","8.5 H Campbell to L Harle, no run","8.6 H Campbell to L Harle, 2 runs, clipped through mid-wicket"],"runs":6,"wkts":0,"rt":71},{"ov":10,"bowl":"R Mundell","t":["2nb","\u2022","\u2022","\u2022","4","4","2"],"sc":[[73,1],[73,1],[73,1],[73,1],[77,1],[81,1],[83,1]],"wd":[null,null,null,null,null,null,null],"bs":[["Jamie Foden",26,30,3,0,86.7],["Lucas Harle",29,29,4,0,100.0],["Lucas Harle",29,30,4,0,96.7],["Lucas Harle",29,31,4,0,93.5],["Lucas Harle",33,32,5,0,103.1],["Lucas Harle",37,33,6,0,112.1],["Lucas Harle",39,34,6,0,114.7]],"sh":[[96.5,38.3,1],null,null,null,[217.4,55.8,4],[216.4,56.8,4],[57.0,43.2,2]],"cm":["9.1 R Mundell to J Foden, 1 run, pulled square on the leg side","9.2 R Mundell to L Harle, no run","9.3 R Mundell to L Harle, no run","9.4 R Mundell to L Harle, no run","9.5 R Mundell to L Harle, <b>FOUR</b>, driven wide of mid-off","9.6 R Mundell to L Harle, <b>FOUR</b>, driven wide of mid-off","9.7 R Mundell to L Harle, 2 runs, pulled backward of square"],"runs":12,"wkts":0,"rt":83},{"ov":11,"bowl":"H Campbell","t":["W","1","wd","2","3","2","1"],"sc":[[83,2],[84,2],[85,2],[87,2],[90,2],[92,2],[93,2]],"wd":[{"o":"Jamie Foden","oab":"J Foden","od":"b H Campbell","or":26,"ob":27,"o4":3,"o6":0,"osr":null,"n":"Lucas Harle","nr":39,"nb":34,"n4":6,"n6":0,"nsr":114.7},null,null,null,null,null,null],"bs":[["Jamie Foden",26,31,3,0,83.9],["Z Leigh",1,1,0,0,100.0],["Lucas Harle",39,35,6,0,111.4],["Lucas Harle",41,36,6,0,113.9],["Lucas Harle",44,37,6,0,118.9],["Z Leigh",3,2,0,0,150.0],["Z Leigh",4,3,0,0,133.3]],"sh":[null,[240.8,34.6,1],null,[303.6,37.9,2],[292.8,38.5,3],[92.1,37.9,2],[205.3,41.2,1]],"cm":["10.1 H Campbell to J Foden, <b>OUT!</b> b H Campbell","10.2 H Campbell to Z Leigh, 1 run, driven through extra cover","10.3 H Campbell to L Harle, no run","10.4 H Campbell to L Harle, 2 runs, edged through the gully","10.5 H Campbell to L Harle, 3 runs, edged through the gully","10.6 H Campbell to Z Leigh, 2 runs, pulled square on the leg side","10.7 H Campbell to Z Leigh, 1 run, driven wide of mid-off"],"runs":10,"wkts":1,"rt":93},{"ov":12,"bowl":"P Swart","t":["1","1","1","1","2","1"],"sc":[[94,2],[95,2],[96,2],[97,2],[99,2],[100,2]],"wd":[null,null,null,null,null,null],"bs":[["Z Leigh",5,4,0,0,125.0],["Lucas Harle",45,38,6,0,118.4],["Z Leigh",6,5,0,0,120.0],["Lucas Harle",46,39,6,0,117.9],["Z Leigh",8,6,0,0,133.3],["Z Leigh",9,7,0,0,128.6]],"sh":[[39.0,28.0,1],[145.3,41.7,1],[198.2,46.4,1],[158.6,53.1,1],[103.4,48.4,2],[204.4,47.4,1]],"cm":["11.1 P Swart to Z Leigh, 1 run, glanced fine down the leg side","11.2 P Swart to L Harle, 1 run, driven over mid-on","11.3 P Swart to Z Leigh, 1 run, driven wide of mid-off","11.4 P Swart to L Harle, 1 run, driven over mid-on","11.5 P Swart to Z Leigh, 2 runs, pulled square on the leg side","11.6 P Swart to Z Leigh, 1 run, driven wide of mid-off"],"runs":7,"wkts":0,"rt":100},{"ov":13,"bowl":"H Campbell","t":["W","wd","1lb","2","2","\u2022","\u2022"],"sc":[[100,3],[101,3],[102,3],[104,3],[106,3],[106,3],[106,3]],"wd":[{"o":"Z Leigh","oab":"Z Leigh","od":"b H Campbell","or":9,"ob":8,"o4":0,"o6":0,"osr":null,"n":"Lucas Harle","nr":46,"nb":39,"n4":6,"n6":0,"nsr":117.9},null,null,null,null,null,null],"bs":[["Z Leigh",9,8,0,0,112.5],["A Shabu",0,1,0,0,0.0],["A Shabu",0,2,0,0,0.0],["Lucas Harle",48,40,6,0,120.0],["Lucas Harle",50,41,6,0,122.0],["Lucas Harle",50,42,6,0,119.0],["Lucas Harle",50,43,6,0,116.3]],"sh":[null,null,null,[58.0,35.1,2],[210.8,42.5,2],null,null],"cm":["12.1 H Campbell to Z Leigh, <b>OUT!</b> b H Campbell","12.2 H Campbell to A Shabu, no run","12.3 H Campbell to A Shabu, no run","12.4 H Campbell to L Harle, 2 runs, pulled backward of square","12.5 H Campbell to L Harle, 2 runs, driven wide of mid-off","12.6 H Campbell to L Harle, no run","12.7 H Campbell to L Harle, no run"],"runs":6,"wkts":1,"rt":106},{"ov":14,"bowl":"P Swart","t":["wd","1","1","1","1lb","1"],"sc":[[107,3],[108,3],[109,3],[110,3],[111,3],[112,3]],"wd":[null,null,null,null,null,null],"bs":[["A Shabu",0,3,0,0,0.0],["A Shabu",1,4,0,0,25.0],["Lucas Harle",51,44,6,0,115.9],["A Shabu",2,5,0,0,40.0],["Lucas Harle",51,45,6,0,113.3],["A Shabu",3,6,0,0,50.0]],"sh":[null,[127.9,40.5,1],[102.3,35.9,1],[97.2,17.2,1],null,[232.4,21.5,1]],"cm":["13.1 P Swart to A Shabu, no run","13.2 P Swart to A Shabu, 1 run, clipped through mid-wicket","13.3 P Swart to L Harle, 1 run, pulled square on the leg side","13.4 P Swart to A Shabu, 1 run, pulled square on the leg side","13.5 P Swart to L Harle, no run","13.6 P Swart to A Shabu, 1 run, driven through extra cover"],"runs":6,"wkts":0,"rt":112},{"ov":15,"bowl":"J Eloff","t":["wd2","1","wd","\u2022","2","6","1","2"],"sc":[[114,3],[115,3],[116,3],[116,3],[118,3],[124,3],[125,3],[127,3]],"wd":[null,null,null,null,null,null,null,null],"bs":[["A Shabu",3,7,0,0,42.9],["Lucas Harle",52,46,6,0,113.0],["A Shabu",3,8,0,0,37.5],["A Shabu",3,9,0,0,33.3],["A Shabu",5,10,0,0,50.0],["A Shabu",11,11,0,1,100.0],["A Shabu",12,12,0,1,100.0],["Lucas Harle",54,47,6,0,114.9]],"sh":[null,[147.1,42.3,1],null,null,[156.5,51.1,2],[217.9,57.4,6],[201.4,33.3,1],[143.5,48.1,2]],"cm":["14.1 J Eloff to A Shabu, no run","14.2 J Eloff to L Harle, 1 run, driven over mid-on","14.3 J Eloff to A Shabu, no run","14.4 J Eloff to A Shabu, no run","14.5 J Eloff to A Shabu, 2 runs, driven over mid-on","14.6 J Eloff to A Shabu, <b>SIX</b>, launched wide of mid-off","14.7 J Eloff to A Shabu, 1 run, driven wide of mid-off","14.8 J Eloff to L Harle, 2 runs, driven over mid-on"],"runs":15,"wkts":0,"rt":127},{"ov":16,"bowl":"P Swart","t":["\u2022","\u2022","W","1","1","2b"],"sc":[[127,3],[127,3],[127,4],[128,4],[129,4],[131,4]],"wd":[null,null,{"o":"A Shabu","oab":"A Shabu","od":"c E Beardwell b P Swart","or":12,"ob":11,"o4":0,"o6":1,"osr":null,"n":"Lucas Harle","nr":54,"nb":47,"n4":6,"n6":0,"nsr":114.9},null,null,null],"bs":[["A Shabu",12,13,0,1,92.3],["A Shabu",12,14,0,1,85.7],["A Shabu",12,15,0,1,80.0],["H Pardesi",1,1,0,0,100.0],["Lucas Harle",55,48,6,0,114.6],["H Pardesi",1,2,0,0,50.0]],"sh":[null,null,null,[156.8,42.9,1],[103.0,33.2,1],null],"cm":["15.1 P Swart to A Shabu, no run","15.2 P Swart to A Shabu, no run","15.3 P Swart to A Shabu, <b>OUT!</b> c E Beardwell b P Swart","15.4 P Swart to H Pardesi, 1 run, driven over mid-on","15.5 P Swart to L Harle, 1 run, pulled square on the leg side","15.6 P Swart to H Pardesi, no run"],"runs":4,"wkts":1,"rt":131}]],"manh":[[[1,9,0,"S Foote",[],[[135.9,56.0,4],[217.7,59.7,4],[133.7,37.7,1]]],[2,13,1,"J Egan",[{"o":"P Swart","oab":"P Swart","od":"c Z Leigh b J Egan","or":13,"ob":10,"o4":3,"o6":0,"osr":null,"n":null,"nr":null,"nb":null,"n4":null,"n6":null,"nsr":null}],[[153.6,57.8,4]]],[3,0,1,"S Foote",[{"o":"H Campbell","oab":"H Campbell","od":"c L Evans b S Foote","or":0,"ob":3,"o4":0,"o6":0,"osr":null,"n":"Theo Clements","nr":0,"nb":2,"n4":0,"n6":0,"nsr":0.0}],[]],[4,13,0,"J Egan",[],[[66.7,43.6,4],[266.4,40.1,2],[312.9,26.8,1]]],[5,0,0,"S Foote",[],[]],[6,3,0,"J Egan",[],[[307.1,37.1,2]]],[7,10,0,"N Cunliffe",[],[[123.6,44.3,1],[245.5,51.5,6],[261.6,42.8,2]]],[8,7,0,"A Shabu",[],[[228.4,56.9,4],[154.6,39.3,1],[273.7,33.8,1],[251.8,39.0,1]]],[9,3,1,"N Cunliffe",[{"o":"M Boxer","oab":"M Boxer","od":"b N Cunliffe","or":11,"ob":20,"o4":0,"o6":1,"osr":null,"n":"Theo Clements","nr":14,"nb":22,"n4":2,"n6":0,"nsr":63.6}],[]],[10,5,0,"A Shabu",[],[[307.3,28.1,1],[103.9,48.9,4]]],[11,5,0,"N Cunliffe",[],[[230.2,30.4,1]]],[12,9,1,"A Shabu",[{"o":"Theo Clements","oab":"T Clements","od":"lbw  b A Shabu","or":26,"ob":34,"o4":4,"o6":0,"osr":null,"n":"Alexander Nunn","nr":1,"nb":9,"n4":0,"n6":0,"nsr":11.1}],[[216.1,39.3,1],[160.7,45.7,2],[215.6,58.9,4]]],[13,4,0,"H Pardesi",[],[[140.0,32.0,1],[94.9,36.8,2],[275.7,29.6,1]]],[14,4,3,"Z Leigh",[{"o":"Alexander Nunn","oab":"A Nunn","od":"ro (L Evans)","or":2,"ob":10,"o4":0,"o6":0,"osr":null,"n":"Reuben Mundell","nr":4,"nb":6,"n4":0,"n6":0,"nsr":66.7},{"o":"Johan Eloff","oab":"J Eloff","od":"b Z Leigh","or":0,"ob":1,"o4":0,"o6":0,"osr":null,"n":"Reuben Mundell","nr":4,"nb":6,"n4":0,"n6":0,"nsr":66.7},{"o":"Reuben Mundell","oab":"R Mundell","od":"ro (Z Leigh)","or":4,"ob":7,"o4":0,"o6":0,"osr":null,"n":"Thomas Mundell","nr":1,"nb":1,"n4":0,"n6":0,"nsr":100.0}],[[142.2,33.0,1],[203.6,41.7,1]]],[15,2,0,"H Pardesi",[],[[221.2,39.9,1],[321.9,29.9,1]]],[16,12,0,"Z Leigh",[],[[205.4,42.5,1],[225.8,56.9,4],[162.3,42.0,1],[154.0,58.7,4]]]],[[1,7,0,"P Swart",[],[]],[2,14,0,"O Bettles",[],[[268.4,42.8,2],[97.0,51.4,4],[98.1,50.3,4],[106.9,51.9,4]]],[3,4,1,"A Nunn",[{"o":"Liam Evans","oab":"L Evans","od":"b A Nunn","or":0,"ob":5,"o4":0,"o6":0,"osr":null,"n":"Jamie Foden","nr":14,"nb":8,"n4":3,"n6":0,"nsr":175.0}],[[151.3,41.6,1],[207.7,46.7,2]]],[4,5,0,"M Boxer",[],[[292.1,48.0,4]]],[5,12,0,"A Nunn",[],[[204.6,37.7,1],[258.7,51.0,4],[317.5,28.2,1],[126.1,34.9,1],[197.8,57.0,4]]],[6,9,0,"M Boxer",[],[[133.7,38.0,1],[293.7,36.6,2],[256.4,43.4,2]]],[7,8,0,"A Nunn",[],[[93.9,45.6,2],[144.1,40.2,1],[124.1,37.4,1],[226.4,35.2,1]]],[8,6,0,"R Mundell",[],[[218.5,43.1,1],[202.0,59.6,4],[68.4,26.1,1]]],[9,6,0,"H Campbell",[],[[103.5,42.1,2],[133.7,36.3,1],[213.2,40.8,1],[115.5,40.6,2]]],[10,12,0,"R Mundell",[],[[96.5,38.3,1],[217.4,55.8,4],[216.4,56.8,4],[57.0,43.2,2]]],[11,10,1,"H Campbell",[{"o":"Jamie Foden","oab":"J Foden","od":"b H Campbell","or":26,"ob":27,"o4":3,"o6":0,"osr":null,"n":"Lucas Harle","nr":39,"nb":34,"n4":6,"n6":0,"nsr":114.7}],[[240.8,34.6,1],[303.6,37.9,2],[292.8,38.5,3],[92.1,37.9,2],[205.3,41.2,1]]],[12,7,0,"P Swart",[],[[39.0,28.0,1],[145.3,41.7,1],[198.2,46.4,1],[158.6,53.1,1],[103.4,48.4,2],[204.4,47.4,1]]],[13,6,1,"H Campbell",[{"o":"Z Leigh","oab":"Z Leigh","od":"b H Campbell","or":9,"ob":8,"o4":0,"o6":0,"osr":null,"n":"Lucas Harle","nr":46,"nb":39,"n4":6,"n6":0,"nsr":117.9}],[[58.0,35.1,2],[210.8,42.5,2]]],[14,6,0,"P Swart",[],[[127.9,40.5,1],[102.3,35.9,1],[97.2,17.2,1],[232.4,21.5,1]]],[15,15,0,"J Eloff",[],[[147.1,42.3,1],[156.5,51.1,2],[217.9,57.4,6],[201.4,33.3,1],[143.5,48.1,2]]],[16,4,1,"P Swart",[{"o":"A Shabu","oab":"A Shabu","od":"c E Beardwell b P Swart","or":12,"ob":11,"o4":0,"o6":1,"osr":null,"n":"Lucas Harle","nr":54,"nb":47,"n4":6,"n6":0,"nsr":114.9}],[[156.8,42.9,1],[103.0,33.2,1]]]]],"shots":[[[135.9,56.0,4,"P Swart"],[217.7,59.7,4,"P Swart"],[133.7,37.7,1,"P Swart"],[153.6,57.8,4,"P Swart"],[66.7,43.6,4,"T Clements"],[266.4,40.1,2,"T Clements"],[312.9,26.8,1,"T Clements"],[307.1,37.1,2,"M Boxer"],[123.6,44.3,1,"T Clements"],[245.5,51.5,6,"M Boxer"],[261.6,42.8,2,"M Boxer"],[228.4,56.9,4,"T Clements"],[154.6,39.3,1,"T Clements"],[273.7,33.8,1,"M Boxer"],[251.8,39.0,1,"T Clements"],[307.3,28.1,1,"A Nunn"],[103.9,48.9,4,"T Clements"],[230.2,30.4,1,"T Clements"],[216.1,39.3,1,"T Clements"],[160.7,45.7,2,"T Clements"],[215.6,58.9,4,"T Clements"],[140.0,32.0,1,"A Nunn"],[94.9,36.8,2,"R Mundell"],[275.7,29.6,1,"R Mundell"],[142.2,33.0,1,"R Mundell"],[203.6,41.7,1,"T Mundell"],[221.2,39.9,1,"T Mundell"],[321.9,29.9,1,"O Bettles"],[205.4,42.5,1,"T Mundell"],[225.8,56.9,4,"O Bettles"],[162.3,42.0,1,"O Bettles"],[154.0,58.7,4,"T Mundell"]],[[268.4,42.8,2,"J Foden"],[97.0,51.4,4,"J Foden"],[98.1,50.3,4,"J Foden"],[106.9,51.9,4,"J Foden"],[151.3,41.6,1,"L Harle"],[207.7,46.7,2,"J Foden"],[292.1,48.0,4,"L Harle"],[204.6,37.7,1,"J Foden"],[258.7,51.0,4,"L Harle"],[317.5,28.2,1,"L Harle"],[126.1,34.9,1,"J Foden"],[197.8,57.0,4,"L Harle"],[133.7,38.0,1,"J Foden"],[293.7,36.6,2,"L Harle"],[256.4,43.4,2,"L Harle"],[93.9,45.6,2,"J Foden"],[144.1,40.2,1,"J Foden"],[124.1,37.4,1,"L Harle"],[226.4,35.2,1,"J Foden"],[218.5,43.1,1,"J Foden"],[202.0,59.6,4,"L Harle"],[68.4,26.1,1,"L Harle"],[103.5,42.1,2,"L Harle"],[133.7,36.3,1,"L Harle"],[213.2,40.8,1,"J Foden"],[115.5,40.6,2,"L Harle"],[96.5,38.3,1,"J Foden"],[217.4,55.8,4,"L Harle"],[216.4,56.8,4,"L Harle"],[57.0,43.2,2,"L Harle"],[240.8,34.6,1,"Z Leigh"],[303.6,37.9,2,"L Harle"],[292.8,38.5,3,"L Harle"],[92.1,37.9,2,"Z Leigh"],[205.3,41.2,1,"Z Leigh"],[39.0,28.0,1,"Z Leigh"],[145.3,41.7,1,"L Harle"],[198.2,46.4,1,"Z Leigh"],[158.6,53.1,1,"L Harle"],[103.4,48.4,2,"Z Leigh"],[204.4,47.4,1,"Z Leigh"],[58.0,35.1,2,"L Harle"],[210.8,42.5,2,"L Harle"],[127.9,40.5,1,"A Shabu"],[102.3,35.9,1,"L Harle"],[97.2,17.2,1,"A Shabu"],[232.4,21.5,1,"A Shabu"],[147.1,42.3,1,"L Harle"],[156.5,51.1,2,"A Shabu"],[217.9,57.4,6,"A Shabu"],[201.4,33.3,1,"A Shabu"],[143.5,48.1,2,"L Harle"],[156.8,42.9,1,"H Pardesi"],[103.0,33.2,1,"L Harle"]]]}