{"id":7174265,"date":"2025-07-27","venue":"Kings Hill Oval","comp":null,"result":"LINTON PARK CC WON BY 9 WICKETS","season":2025,"home":"Kings Hill CC","away":"Linton Park CC","inns":[{"team":"Kings Hill CC","total":157,"wkts":"10","overs":"38.2","extras":"18  (4b, 10w, 4nb )","linton":0,"bat":[[1,"Paul Rothwell","b Farhan Malik",4,0,0,0,0],[2,"Rayan Bhatti","c Farhan Malik b Divan Tromp",14,0,0,0,0],[3,"Charlie Barnard","b Farhan Malik",0,0,0,0,1],[4,"Graham Hutchins","c Aaron Hughes b John Karassellos",29,0,0,0,0],[5,"Connor Smith","run out Unsure",0,0,0,0,1],[6,"Quintin Joubert","c Christian Eloff b Divan Tromp",1,0,0,0,0],[7,"Adam Lowing","b Nick Tromp",38,0,0,0,0],[8,"Tom Bray","b Divan Tromp",4,0,0,0,0],[9,"Matthew Milson","b Johan Eloff",9,0,0,0,0],[10,"Matthew Blewett","c Rahul Parakh b Nick Tromp",25,0,0,0,0],[11,"Liam Dudgeon-Smith","not out",15,0,0,0,0]],"bowl":[["Farhan Malik","5",1,27,2,0,0],["Christian Eloff","6",1,18,0,0,0],["John Karassellos","5",1,23,1,0,0],["Divan Tromp","4",0,16,3,0,0],["Johan Eloff","5",0,18,1,0,0],["Daniel Baker","3",1,5,0,0,0],["Rahul Parakh","3",0,16,0,0,0],["Nick Tromp","4.2",0,11,2,0,0],["Anthony Karassellos","3",0,19,0,0,0]],"fow":[]},{"team":"Linton Park CC","total":159,"wkts":"1","overs":"20.2","extras":"9  (2b, 3lb, 3w, 1nb )","linton":1,"bat":[[1,"Johan Eloff","b Tom Bray",6,0,0,0,0],[2,"Anthony Karassellos","retired not out",102,0,0,0,0],[3,"Aaron Hughes","retired not out",29,0,0,0,0],[4,"Daniel Baker","not out",11,0,0,0,0],[5,"Christian Eloff","not out",2,0,0,0,0]],"bowl":[["Tom Bray","4",0,15,1,0,0],["Liam Dudgeon-Smith","3",0,27,0,0,0],["Matthew Blewett","3",0,34,0,0,0],["Rayan Bhatti","4",0,35,0,0,0],["Matthew Milson","4",0,25,0,0,0],["Connor Smith","2.2",0,18,0,0,0]],"fow":[]}],"mvp":{"Johan Eloff":2,"Anthony Karassellos":9,"Aaron Hughes":3,"Daniel Baker":2,"Christian Eloff":3,"Farhan Malik":4,"John Karassellos":2,"Divan Tromp":5,"Rahul Parakh":2,"Nick Tromp":4},"mvdh":{}}